obsender/__init__.py
obsender/common.py
obsender/config.py
obsender/constants.py
obsender/decorators.py
obsender/exceptions.py
obsender/multi_sender.py
obsender/senders.py
obsender/tests/__init__.py
obsender/tests/unit/__init__.py
obsender/tests/unit/senders/__init__.py
obsender/tests/unit/senders/test_dummy.py
obsender/tests/unit/senders/test_victoria_metrics.py
obsender/tests/unit/vm_client/__init__.py
obsender/tests/unit/vm_client/test_helpers.py
obsender/tests/unit/vm_client/test_push.py
obsender/vm_client/__init__.py
obsender/vm_client/helpers.py
obsender/vm_client/protocol.py
obsender/vm_client/push.py
obsender-5.0.0.dist-info/licenses/AUTHORS
obsender-5.0.0.dist-info/METADATA
obsender-5.0.0.dist-info/WHEEL
obsender-5.0.0.dist-info/pbr.json
obsender-5.0.0.dist-info/top_level.txt
obsender-5.0.0.dist-info/RECORD
