Metadata-Version: 2.4
Name: obsender
Version: 5.0.0
Summary: Infra metric sending Library
Home-page: https://github.com/vktechdev/obsender
Author: VK Tech
Author-email: all-infra.mail.ru@we.mail.ru
Classifier: Environment :: Other Environment
Classifier: Intended Audience :: Developers
Classifier: License :: OSI Approved :: Apache Software License
Classifier: Operating System :: POSIX :: Linux
Classifier: Programming Language :: Python
Classifier: Programming Language :: Python :: 2
Classifier: Programming Language :: Python :: 2.7
Classifier: Programming Language :: Python :: 3
Classifier: Programming Language :: Python :: 3.2
Classifier: Programming Language :: Python :: 3.3
Classifier: Programming Language :: Python :: 3.4
Classifier: Programming Language :: Python :: 3.5
Classifier: Programming Language :: Python :: 3.6
Classifier: Programming Language :: Python :: 3.8
License-File: AUTHORS
Requires-Dist: six<=5.8.1,>=1.10.0
Requires-Dist: requests<=2.32.3,>=2.12.5
Requires-Dist: futures<=3.3.0; python_version == "2.7" or python_version == "2.6"
Requires-Dist: monotonic>=0.6; python_version < "3"
Provides-Extra: osloconfig
Requires-Dist: oslo.config==6.7.0; extra == "osloconfig"
Provides-Extra: test
Requires-Dist: hacking==2.0.0; extra == "test"
Requires-Dist: mock==2.0.0; extra == "test"
Requires-Dist: pytest<9.0.0,>=8.0.0; extra == "test"
Requires-Dist: pytest-timer<2.0.0,>=1.0.0; extra == "test"
Requires-Dist: pytest-cov<7.0.0,>=5.0.0; extra == "test"
Dynamic: author
Dynamic: author-email
Dynamic: classifier
Dynamic: description
Dynamic: home-page
Dynamic: license-file
Dynamic: provides-extra
Dynamic: requires-dist
Dynamic: summary
